{
  "electricity_models": [
    {
      "model": "XGBoost",
      "rmse": 1089.8205424618502,
      "mae": 867.0740052812885,
      "r2": 0.922409492590061,
      "timestamp": "2026-02-22T02:16:05.371986"
    },
    {
      "model": "Gradient Boosting",
      "rmse": 1057.3848277740087,
      "mae": 840.7186594747067,
      "r2": 0.9269593278139006,
      "timestamp": "2026-02-22T02:16:09.460306"
    }
  ],
  "training_samples": 13747,
  "test_samples": 3437,
  "features": [
    "hour",
    "day_of_week",
    "month",
    "day_of_year",
    "week_of_year",
    "demand_lag_1",
    "demand_lag_2",
    "demand_lag_48",
    "demand_lag_336"
  ]
}